pharos/__init__.py
pharos/__version__.py
pharos/app.py
pharos/dist/index.html
pharos/dist/sdk.5453a15c4c09ea0262f2.js
pharos/dist/sdk.e41e7bd45dc6de89c3a0.js
pharos/dist/style.5453a15c4c09ea0262f2.css
pharos/dist/style.e41e7bd45dc6de89c3a0.css
pharos/dist/static/moon.3b038e20.svg
pharos/dist/static/moon.7b647672.ttf
pharos/dist/static/moon.c76e5d37.woff
pharos/dist/visualization/G.svg
pharos/dist/visualization/Graviti.svg
pharos/dist/visualization/api-failed.svg
pharos/dist/visualization/empty-black.png
pharos/dist/visualization/empty-white.png
pharos/dist/visualization/favicon.svg
pharos/dist/visualization/help1-black.png
pharos/dist/visualization/help1-white.png
pharos/dist/visualization/help2-black.png
pharos/dist/visualization/help2-white.png
pharos/dist/visualization/help3-black.png
pharos/dist/visualization/help3-white.png
pharos/dist/visualization/rotate.svg
pharos/dist/visualization/tip.png
pharos/dist/visualization/workers/BINDecoderWorker.js
pharos/dist/visualization/workers/PCDDecoderWorker.js
pharos/dist/visualization/workers/PLYDecoderWorker.js
pharos-0.2.0.dist-info/METADATA
pharos-0.2.0.dist-info/WHEEL
pharos-0.2.0.dist-info/top_level.txt
pharos-0.2.0.dist-info/RECORD
